celestialflow/__init__.py
celestialflow/task_executor.py
celestialflow/task_graph.py
celestialflow/task_logging.py
celestialflow/task_nodes.py
celestialflow/task_progress.py
celestialflow/task_queue.py
celestialflow/task_report.py
celestialflow/task_stage.py
celestialflow/task_structure.py
celestialflow/task_tools.py
celestialflow/task_types.py
celestialflow/task_web.py
celestialflow/static/favicon.ico
celestialflow/static/css/base.css
celestialflow/static/css/dashboard.css
celestialflow/static/css/errors.css
celestialflow/static/css/inject.css
celestialflow/static/js/main.js
celestialflow/static/js/task_errors.js
celestialflow/static/js/task_injection.js
celestialflow/static/js/task_statuses.js
celestialflow/static/js/task_structure.js
celestialflow/static/js/task_summary.js
celestialflow/static/js/task_topology.js
celestialflow/static/js/utils.js
celestialflow/templates/index.html
celestialflow-3.1.0.dist-info/METADATA
celestialflow-3.1.0.dist-info/WHEEL
celestialflow-3.1.0.dist-info/entry_points.txt
celestialflow-3.1.0.dist-info/top_level.txt
celestialflow-3.1.0.dist-info/RECORD
