Metadata-Version: 2.4
Name: celestialflow
Version: 3.1.0
Summary: A flexible GRAPH-based task orchestration framework.
Author-email: Mr-xiaotian <mingxiaomingtian@gmail.com>
License: MIT
Project-URL: Homepage, https://github.com/Mr-xiaotian/CelestialFlow
Project-URL: Bug Tracker, https://github.com/Mr-xiaotian/CelestialFlow/issues
Keywords: workflow,task,graph,async,CelestialFlow
Classifier: Programming Language :: Python :: 3
Classifier: License :: OSI Approved :: MIT License
Classifier: Operating System :: OS Independent
Classifier: Framework :: FastAPI
Classifier: Topic :: Software Development :: Libraries
Requires-Python: >=3.8
Requires-Dist: tqdm
Requires-Dist: loguru
Requires-Dist: fastapi
Requires-Dist: uvicorn
Requires-Dist: requests
Requires-Dist: networkx
Requires-Dist: redis
Requires-Dist: jinja2
Requires-Dist: celestialtree
